nostr_mirror/__init__.py
nostr_mirror/main.py
nostr_mirror/tweet_db.py
nostr_mirror/tweet_to_nostr.py
nostr_mirror/twitter_rss_data.py
nostr_mirror/twitter_rssbox.py
nostr_mirror-0.1.0.dist-info/LICENSE
nostr_mirror-0.1.0.dist-info/METADATA
nostr_mirror-0.1.0.dist-info/WHEEL
nostr_mirror-0.1.0.dist-info/RECORD
