Metadata-Version: 2.1
Name: nostr-mirror
Version: 0.1.0
Summary: 
Author: kchro3
Author-email: jhara1418@gmail.com
Requires-Python: >=3.9.6,<4.0.0
Classifier: Programming Language :: Python :: 3
Classifier: Programming Language :: Python :: 3.10
Classifier: Programming Language :: Python :: 3.11
Requires-Dist: fire (>=0.5.0,<0.6.0)
Requires-Dist: pynostr (>=0.6.2,<0.7.0)
Requires-Dist: setuptools (>=67.6.0,<68.0.0)
